requests_testing.py
test_requests_testing.py
requests_testing-0.2.0.dist-info/DESCRIPTION.rst
requests_testing-0.2.0.dist-info/METADATA
requests_testing-0.2.0.dist-info/RECORD
requests_testing-0.2.0.dist-info/WHEEL
requests_testing-0.2.0.dist-info/metadata.json
requests_testing-0.2.0.dist-info/top_level.txt
