Metadata-Version: 2.0
Name: requests-testing
Version: 0.2.0
Summary: A utility library for mocking out the `requests` Python library.
Home-page: https://github.com/a-pertsev/requests-testing
Author: Pertsev Alexey
Author-email: oeermanz@gmail.com
License: Apache 2.0
Keywords: requests mock testing
Platform: UNKNOWN
Classifier: Development Status :: 4 - Beta
Classifier: Intended Audience :: Developers
Classifier: Intended Audience :: Information Technology
Classifier: Operating System :: OS Independent
Classifier: Programming Language :: Python :: 2
Classifier: Programming Language :: Python :: 2.7
Classifier: Programming Language :: Python :: 3
Classifier: Topic :: Software Development
Requires-Dist: requests (>=2.0)
Requires-Dist: cookies
Requires-Dist: six
Requires-Dist: mock
Provides-Extra: tests
Requires-Dist: pytest; extra == 'tests'
Requires-Dist: coverage (<5.0.0,>=3.7.1); extra == 'tests'
Requires-Dist: pytest-cov; extra == 'tests'
Requires-Dist: pytest-localserver; extra == 'tests'
Requires-Dist: flake8; extra == 'tests'
Requires-Dist: idna; extra == 'tests'
